<?xml version="1.0" encoding="UTF-8"?>
<Audio version="1.0" gain="-10dB">
    <Chain>
        <!-- One sawtooth -->
        <Mixer>
            <OscillatorNode type="sawtooth">
                <frequency follow="freqValue, change, e.target.value" map="0,100,60,72,MIDI"></frequency>
            </OscillatorNode>
            
            <Send output="#saw-tone"></Send>
        </Mixer>

        <GainNode id="saw-tone">
            <gain value="0" follow="sawtone, change, e.target.value"></gain>
            <Send output="#overall-gain"></Send>
        </GainNode>
    </Chain>

    <Chain>
        <!-- Sawtooth chord -->
        <Mixer>
            <OscillatorNode type="sawtooth">
                <frequency follow="freqValue, change, e.target.value" map="0,100,60,72,MIDI"></frequency>
            </OscillatorNode>

            <OscillatorNode type="sawtooth">
                <frequency follow="freqValue, change, e.target.value" map="0,100,64,76,MIDI"></frequency>
            </OscillatorNode>

            <OscillatorNode type="sawtooth">
                <frequency follow="freqValue, change, e.target.value" map="0,100,67,79,MIDI"></frequency>
            </OscillatorNode>
            
            <Send output="#saw-chord"></Send>
        </Mixer>

        <GainNode id="saw-chord">
            <gain value="0" follow="sawchord, change, e.target.value"></gain>
            <Send output="#overall-gain"></Send>
        </GainNode>
    </Chain>

    <Chain>
        <!-- One sine -->
        <Mixer>
            <OscillatorNode type="sine">
                <frequency follow="freqValue, change, e.target.value" map="0,100,60,72,MIDI"></frequency>
            </OscillatorNode>
            
            <Send output="#sine-tone"></Send>
        </Mixer>

        <GainNode id="sine-tone">
            <gain value="0" follow="sinetone, change, e.target.value"></gain>
            <Send output="#overall-gain"></Send>
        </GainNode>
    </Chain>

    <Chain>
        <!-- Sine chord -->
        <Mixer>
            <OscillatorNode type="sine">
                <frequency follow="freqValue, change, e.target.value" map="0,100,60,72,MIDI"></frequency>
            </OscillatorNode>

            <OscillatorNode type="sine">
                <frequency follow="freqValue, change, e.target.value" map="0,100,64,76,MIDI"></frequency>
            </OscillatorNode>

            <OscillatorNode type="sine">
                <frequency follow="freqValue, change, e.target.value" map="0,100,67,79,MIDI"></frequency>
            </OscillatorNode>
            
            <Send output="#sine-chord"></Send>
        </Mixer>

        <GainNode id="sine-chord">
            <gain value="0" follow="sinechord, change, e.target.value"></gain>
            <Send output="#overall-gain"></Send>
        </GainNode>
    </Chain>

    <GainNode id="overall-gain">
        <gain value="0" follow="volslider, input, e.target.value"></gain>
    </GainNode>
</Audio>